cpp_pyqubo.cpython-310-darwin.so
pyqubo/__init__.py
pyqubo/array.py
pyqubo/logic.py
pyqubo/logical_constraint.py
pyqubo/package_info.py
pyqubo/integer/__init__.py
pyqubo/integer/integer.py
pyqubo/integer/log_encoded_integer.py
pyqubo/integer/one_hot_enc_integer.py
pyqubo/integer/order_enc_integer.py
pyqubo/integer/unary_encoded_integer.py
pyqubo/utils/__init__.py
pyqubo/utils/asserts.py
pyqubo/utils/solver.py
pyqubo2-1.4.0.dist-info/LICENSE
pyqubo2-1.4.0.dist-info/METADATA
pyqubo2-1.4.0.dist-info/WHEEL
pyqubo2-1.4.0.dist-info/top_level.txt
pyqubo2-1.4.0.dist-info/RECORD
