Metadata-Version: 2.1
Name: pyqubo2
Version: 1.4.0
Summary: PyQUBO allows you to create QUBOs or Ising models from mathematical expressions with support for Python 3.12
Home-page: https://github.com/MXNXV-ERR/pyqubo
Author: MXNXV-ERR
Author-email: angbymtg@gmail.com
Maintainer: MXNXV-ERR
Maintainer-email: angbymtg@gmail.com
License: Apache 2.0
Download-URL: https://github.com/MXNXV-ERR/pyqubo
Keywords: QUBO,quantum annealing,annealing machine,ising model,optimization
Platform: UNKNOWN
Classifier: Programming Language :: Python :: 3.5
Classifier: Programming Language :: Python :: 3.6
Classifier: Programming Language :: Python :: 3.7
Classifier: Programming Language :: Python :: 3.8
Classifier: Programming Language :: Python :: 3.9
Classifier: License :: OSI Approved :: Apache Software License
Requires-Python: >=3.6, <3.13
License-File: LICENSE
